win32more/Microsoft/Foundation/__init__.py
win32more/Microsoft/Graphics/DirectX/__init__.py
win32more/Microsoft/Graphics/Display/__init__.py
win32more/Microsoft/Graphics/Imaging/__init__.py
win32more/Microsoft/Security/Authentication/OAuth/__init__.py
win32more/Microsoft/UI/__init__.py
win32more/Microsoft/UI/Composition/__init__.py
win32more/Microsoft/UI/Composition/Core/__init__.py
win32more/Microsoft/UI/Composition/Diagnostics/__init__.py
win32more/Microsoft/UI/Composition/Effects/__init__.py
win32more/Microsoft/UI/Composition/Interactions/__init__.py
win32more/Microsoft/UI/Composition/Scenes/__init__.py
win32more/Microsoft/UI/Composition/SystemBackdrops/__init__.py
win32more/Microsoft/UI/Content/__init__.py
win32more/Microsoft/UI/Dispatching/__init__.py
win32more/Microsoft/UI/Input/__init__.py
win32more/Microsoft/UI/Input/DragDrop/__init__.py
win32more/Microsoft/UI/Input/Interop/__init__.py
win32more/Microsoft/UI/System/__init__.py
win32more/Microsoft/UI/Text/__init__.py
win32more/Microsoft/UI/Windowing/__init__.py
win32more/Microsoft/UI/Xaml/__init__.py
win32more/Microsoft/UI/Xaml/Automation/__init__.py
win32more/Microsoft/UI/Xaml/Automation/Peers/__init__.py
win32more/Microsoft/UI/Xaml/Automation/Provider/__init__.py
win32more/Microsoft/UI/Xaml/Automation/Text/__init__.py
win32more/Microsoft/UI/Xaml/Controls/__init__.py
win32more/Microsoft/UI/Xaml/Controls/AnimatedVisuals/__init__.py
win32more/Microsoft/UI/Xaml/Controls/Primitives/__init__.py
win32more/Microsoft/UI/Xaml/Data/__init__.py
win32more/Microsoft/UI/Xaml/Documents/__init__.py
win32more/Microsoft/UI/Xaml/Hosting/__init__.py
win32more/Microsoft/UI/Xaml/Input/__init__.py
win32more/Microsoft/UI/Xaml/Interop/__init__.py
win32more/Microsoft/UI/Xaml/Markup/__init__.py
win32more/Microsoft/UI/Xaml/Media/__init__.py
win32more/Microsoft/UI/Xaml/Media/Animation/__init__.py
win32more/Microsoft/UI/Xaml/Media/Imaging/__init__.py
win32more/Microsoft/UI/Xaml/Media/Media3D/__init__.py
win32more_microsoft_windowsappsdk-0.8.1.8.260101001.dist-info/METADATA
win32more_microsoft_windowsappsdk-0.8.1.8.260101001.dist-info/WHEEL
win32more_microsoft_windowsappsdk-0.8.1.8.260101001.dist-info/licenses/LICENSE (Microsoft.WindowsAppSDK).txt
win32more_microsoft_windowsappsdk-0.8.1.8.260101001.dist-info/RECORD
