Metadata-Version: 2.4
Name: win32more-Microsoft.WindowsAppSDK
Version: 0.8.1.8.260101001
License-File: LICENSE (Microsoft.WindowsAppSDK).txt
Requires-Dist: win32more-core==0.8.*
Requires-Dist: win32more-microsoft-web-webview2<0.9,>=0.8.1.0.3179.45
